chunky_upload/__init__.py
chunky_upload/admin.py
chunky_upload/apps.py
chunky_upload/constants.py
chunky_upload/exceptions.py
chunky_upload/response.py
chunky_upload/settings.py
chunky_upload/signals.py
chunky_upload/urls.py
chunky_upload/management/__init__.py
chunky_upload/management/commands/__init__.py
chunky_upload/management/commands/delete_expired_uploads.py
chunky_upload/migrations/0001_initial.py
chunky_upload/migrations/__init__.py
chunky_upload/models/__init__.py
chunky_upload/models/abstract_models.py
chunky_upload/models/models.py
chunky_upload/views/__init__.py
chunky_upload/views/base_views.py
chunky_upload/views/views.py
chunky_upload/views/helpers/__init__.py
chunky_upload/views/helpers/is_authenticated.py
django_chunky_upload-1.0.3.dist-info/LICENSE.txt
django_chunky_upload-1.0.3.dist-info/METADATA
django_chunky_upload-1.0.3.dist-info/WHEEL
django_chunky_upload-1.0.3.dist-info/top_level.txt
django_chunky_upload-1.0.3.dist-info/RECORD
