Metadata-Version: 2.1
Name: django-chunky-upload
Version: 1.0.3
Summary: Upload large files to Django in multiple chunks, with the ability to resume if the upload is interrupted.
Home-page: https://github.com/Vader19695/django-chunky-upload
Download-URL: https://github.com/Vader19695/django-chunky-upload/tarball/1.0.3
Author: Jaryd Rester
Author-email: pypi@jarydrester.com
License: MIT-Zero
Platform: UNKNOWN
Requires-Python: >=3.7
License-File: LICENSE.txt
